{"pageIndex":0,"pageSize":12,"totalCount":106,"data":[{"id":27512,"name":"OPPO R17","topPrice":2226,"imgUrl":"https://sr.aihuishou.com/image/5b875ea90527ada80a000001.png","categoryId":1,"brandId":4,"totalRecycleCount":0,"isNative":false},{"id":27170,"name":"OPPO Find X","topPrice":3339,"imgUrl":"https://sr.aihuishou.com/image/5b480b5a3b95dd687c000001.png","categoryId":1,"brandId":4,"totalRecycleCount":0,"isNative":false},{"id":19664,"name":"OPPO R9","topPrice":525,"imgUrl":"https://sr.aihuishou.com/image/5a336c1f3a32e4700f00005d.png","categoryId":1,"brandId":4,"totalRecycleCount":0,"isNative":false},{"id":23640,"name":"OPPO R9s","topPrice":536,"imgUrl":"https://sr.aihuishou.com/image/5a336c3110a81c0000000059.png","categoryId":1,"brandId":4,"totalRecycleCount":0,"isNative":false},{"id":20692,"name":"OPPO A37","topPrice":231,"imgUrl":"https://sr.aihuishou.com/image/5a3367f410a81c0000000015.png","categoryId":1,"brandId":4,"totalRecycleCount":0,"isNative":false},{"id":23819,"name":"OPPO A57 ","topPrice":504,"imgUrl":"https://sr.aihuishou.com/image/5a336a943a32e4700f000025.png","categoryId":1,"brandId":4,"totalRecycleCount":0,"isNative":false},{"id":25170,"name":"OPPO R11","topPrice":987,"imgUrl":"https://sr.aihuishou.com/image/5a337de93a32e4700f000125.png","categoryId":1,"brandId":4,"totalRecycleCount":0,"isNative":false},{"id":26428,"name":"OPPO R15","topPrice":1418,"imgUrl":"https://sr.aihuishou.com/image/5aafc9d378d7bd00000000b5.png","categoryId":1,"brandId":4,"totalRecycleCount":0,"isNative":false},{"id":27756,"name":"OPPO R17 Pro","topPrice":2867,"imgUrl":"https://sr.aihuishou.com/image/5bc40a49230aba000000000f.png","categoryId":1,"brandId":4,"totalRecycleCount":0,"isNative":false},{"id":23614,"name":"OPPO A59s","topPrice":378,"imgUrl":"https://sr.aihuishou.com/image/5a336aa83a32e4700f00002d.png","categoryId":1,"brandId":4,"totalRecycleCount":0,"isNative":false},{"id":27253,"name":"OPPO A5","topPrice":735,"imgUrl":"https://sr.aihuishou.com/image/5b48548bebcae00000000009.png","categoryId":1,"brandId":4,"totalRecycleCount":0,"isNative":false},{"id":25950,"name":"OPPO R11s ","topPrice":1029,"imgUrl":"https://sr.aihuishou.com/image/5a337e2310a81c0000000139.png","categoryId":1,"brandId":4,"totalRecycleCount":0,"isNative":false}],"code":200,"message":null,"resultMessage":null}