{"pageIndex":13,"pageSize":12,"totalCount":178,"data":[{"id":21262,"name":"金立 GN880E","topPrice":2,"imgUrl":"https://sr.aihuishou.com/image/5a3cc533c911530000000145.png","categoryId":1,"brandId":278,"totalRecycleCount":0,"isNative":false},{"id":21289,"name":"金立 E701","topPrice":2,"imgUrl":"https://sr.aihuishou.com/image/5a3cb422527fdd0c0f000019.png","categoryId":1,"brandId":278,"totalRecycleCount":0,"isNative":false},{"id":16211,"name":"金立 C620","topPrice":2,"imgUrl":"https://sr.aihuishou.com/image/5a3cb379527fdd0c0f00000d.png","categoryId":1,"brandId":278,"totalRecycleCount":0,"isNative":false},{"id":21259,"name":"金立 V305","topPrice":2,"imgUrl":"https://sr.aihuishou.com/image/5a3cbd8b39c51a100a000099.png","categoryId":1,"brandId":278,"totalRecycleCount":0,"isNative":false},{"id":21291,"name":"金立 TD188","topPrice":2,"imgUrl":"https://sr.aihuishou.com/image/5a3cc5c4c91153000000016d.png","categoryId":1,"brandId":278,"totalRecycleCount":0,"isNative":false},{"id":21286,"name":"金立 A919","topPrice":2,"imgUrl":"https://sr.aihuishou.com/image/5a3cc25839c51a100a0000b1.png","categoryId":1,"brandId":278,"totalRecycleCount":0,"isNative":false},{"id":21064,"name":"金立 M5 Mini","topPrice":60,"imgUrl":"https://sr.aihuishou.com/image/5a435f904f3af30000000005.png","categoryId":1,"brandId":278,"totalRecycleCount":0,"isNative":false},{"id":21269,"name":"金立 TD216","topPrice":2,"imgUrl":"https://sr.aihuishou.com/image/5a3cc5da39c51a100a0000dd.png","categoryId":1,"brandId":278,"totalRecycleCount":0,"isNative":false},{"id":21252,"name":"金立 GN330","topPrice":2,"imgUrl":"https://sr.aihuishou.com/image/5a3cc4c139c51a100a0000c9.png","categoryId":1,"brandId":278,"totalRecycleCount":0,"isNative":false},{"id":17445,"name":"金立 V188","topPrice":10,"imgUrl":"https://sr.aihuishou.com/image/5a3cbd7339c51a100a000095.png","categoryId":1,"brandId":278,"totalRecycleCount":0,"isNative":false},{"id":17251,"name":"金立 GN380","topPrice":2,"imgUrl":"https://sr.aihuishou.com/image/5a3cb928c91153000000006d.png","categoryId":1,"brandId":278,"totalRecycleCount":0,"isNative":false},{"id":21270,"name":"金立 C500","topPrice":2,"imgUrl":"https://sr.aihuishou.com/image/5a3cb361c911530000000011.png","categoryId":1,"brandId":278,"totalRecycleCount":0,"isNative":false}],"code":200,"message":null,"resultMessage":null}