{"pageIndex":1,"pageSize":12,"totalCount":63,"data":[{"id":24511,"name":"红辣椒Note4x","topPrice":40,"imgUrl":"https://sr.aihuishou.com/image/5a6c31cd7f6a07000000005d.png","categoryId":1,"brandId":463,"totalRecycleCount":0,"isNative":false},{"id":24507,"name":"红辣椒Note3","topPrice":50,"imgUrl":"https://sr.aihuishou.com/image/5a6c31c27f6a070000000059.png","categoryId":1,"brandId":463,"totalRecycleCount":0,"isNative":false},{"id":24528,"name":"红辣椒Q6","topPrice":2,"imgUrl":"https://sr.aihuishou.com/image/5a6c322e7f6a070000000065.png","categoryId":1,"brandId":463,"totalRecycleCount":0,"isNative":false},{"id":24530,"name":"小辣椒X6","topPrice":2,"imgUrl":"https://sr.aihuishou.com/image/5a6c333148bbdbfc1400009d.png","categoryId":1,"brandId":463,"totalRecycleCount":0,"isNative":false},{"id":24526,"name":"红辣椒金典JD-Plus","topPrice":40,"imgUrl":"https://sr.aihuishou.com/image/5a6c327548bbdbfc14000075.png","categoryId":1,"brandId":463,"totalRecycleCount":0,"isNative":false},{"id":25235,"name":"小辣椒S7","topPrice":50,"imgUrl":"https://sr.aihuishou.com/image/5a6c32eb7f6a070000000089.png","categoryId":1,"brandId":463,"totalRecycleCount":0,"isNative":false},{"id":27699,"name":"红辣椒6","topPrice":60,"imgUrl":"https://sr.aihuishou.com/image/5bb4ab22e4cd764c32000009.png","categoryId":1,"brandId":463,"totalRecycleCount":0,"isNative":false},{"id":24508,"name":"红辣椒Note3 Pro","topPrice":40,"imgUrl":"https://sr.aihuishou.com/image/5a6c31b348bbdbfc1400005d.png","categoryId":1,"brandId":463,"totalRecycleCount":0,"isNative":false},{"id":25481,"name":"红辣椒4A","topPrice":10,"imgUrl":"https://sr.aihuishou.com/image/5a6c2b2e48bbdbfc1400004d.png","categoryId":1,"brandId":463,"totalRecycleCount":0,"isNative":false},{"id":27668,"name":"红辣椒GM-T33S","topPrice":10,"imgUrl":"https://sr.aihuishou.com/image/5ba9f6f85abed5502300006c.png","categoryId":1,"brandId":463,"totalRecycleCount":0,"isNative":false},{"id":27630,"name":"小辣椒S9","topPrice":60,"imgUrl":"https://sr.aihuishou.com/image/5ba339d4e38bb01c30000017.png","categoryId":1,"brandId":463,"totalRecycleCount":0,"isNative":false},{"id":24934,"name":"红辣椒Q5","topPrice":10,"imgUrl":"https://sr.aihuishou.com/image/5a6c2b377f6a07000000004d.png","categoryId":1,"brandId":463,"totalRecycleCount":0,"isNative":false}],"code":200,"message":null,"resultMessage":null}