{"pageIndex":0,"pageSize":12,"totalCount":42,"data":[{"id":26977,"name":"天语 X11","topPrice":80,"imgUrl":"https://sr.aihuishou.com/image/5b19ede38744be0000000009.png","categoryId":1,"brandId":12,"totalRecycleCount":0,"isNative":false},{"id":24166,"name":"天语 X7Pro","topPrice":40,"imgUrl":"https://sr.aihuishou.com/image/588725c6c721a35c14000009.png","categoryId":1,"brandId":12,"totalRecycleCount":0,"isNative":false},{"id":26812,"name":"天语 8848 Note5","topPrice":40,"imgUrl":"https://sr.aihuishou.com/image/5b04f0113b9e65000000000b.png","categoryId":1,"brandId":12,"totalRecycleCount":0,"isNative":false},{"id":26269,"name":"天语 X9 Plus","topPrice":70,"imgUrl":"https://sr.aihuishou.com/image/5a69b5e11436910000000012.png","categoryId":1,"brandId":12,"totalRecycleCount":0,"isNative":false},{"id":26543,"name":"天语 8818","topPrice":80,"imgUrl":"https://sr.aihuishou.com/image/5ad026d61ae518000000000e.png","categoryId":1,"brandId":12,"totalRecycleCount":0,"isNative":false},{"id":9646,"name":"天语 C966e","topPrice":2,"imgUrl":"https://sr.aihuishou.com/image/53ba709817bbe3982200002d.png","categoryId":1,"brandId":12,"totalRecycleCount":0,"isNative":false},{"id":10165,"name":"天语 Touch 3","topPrice":5,"imgUrl":"https://sr.aihuishou.com/image/53ba709cc50245081b000049.png","categoryId":1,"brandId":12,"totalRecycleCount":0,"isNative":false},{"id":9282,"name":"天语 U86（大黄蜂Kiss）","topPrice":2,"imgUrl":"https://sr.aihuishou.com/image/53ba709a17bbe39822000041.png","categoryId":1,"brandId":12,"totalRecycleCount":0,"isNative":false},{"id":8490,"name":"天语 E800","topPrice":2,"imgUrl":"https://sr.aihuishou.com/image/53ab87576b3e92c4250009de.png","categoryId":1,"brandId":12,"totalRecycleCount":0,"isNative":false},{"id":9813,"name":"天语 T800c","topPrice":2,"imgUrl":"https://sr.aihuishou.com/image/53ba709bc50245081b000045.png","categoryId":1,"brandId":12,"totalRecycleCount":0,"isNative":false},{"id":10085,"name":"天语 E619+","topPrice":2,"imgUrl":"https://sr.aihuishou.com/image/53ba709ac50245081b00003d.png","categoryId":1,"brandId":12,"totalRecycleCount":0,"isNative":false},{"id":17813,"name":"天语 L820","topPrice":5,"imgUrl":"https://sr.aihuishou.com/image/5620a2042dddcabc41000242.png","categoryId":1,"brandId":12,"totalRecycleCount":0,"isNative":false}],"code":200,"message":null,"resultMessage":null}